Workbook

Sheet Financial Inputs
A1: Risk Quantification Inputs
A3: Total Contract Value (EUR) | B3: 100000000 | C3: Editable project input
A4: Low probability factor | B4: 0.15 | C4: Screening assumption
A5: Medium probability factor | B5: 0.4 | C5: Screening assumption
A6: High probability factor | B6: 0.7 | C6: Screening assumption
A7: Default mitigation effectiveness | B7: 0.35 | C7: Editable expected reduction in EMV

Sheet Financial Summary
A1: Portfolio Risk Exposure Summary
A3: Total Contract Value | B3: ='Financial Inputs'!B3 -> 100000000
A4: Sum of gross exposures | B4: =SUM('Risk Library'!O2:O3001) -> 5790000000
A5: Sum of expected monetary values | B5: =SUM('Risk Library'!Q2:Q3001) -> 2916000000
A6: Sum of residual expected exposures | B6: =SUM('Risk Library'!S2:S3001) -> 1895400000
A7: Residual exposure / TCV | B7: =B6/B3 -> 18.954
A9: Important aggregation warning | B9: The simple sum assumes independent risks and can overstate portfolio exposure where risks overlap or are mutually exclusive. Use Monte Carlo or dependency modelling for contingency setting.

Sheet Risk Library
A1: Risk ID | B1: Risk Statement | C1: Risk Category | D1: Project Type | E1: Energy Segment | F1: Geographic Context | G1: Lifecycle Phase | H1: Employer / Contractor / Shared allocation | I1: Probability (L/M/H) | J1: Impact (Cost / Time / Quality / HSE) | K1: Mitigation Actions | L1: Early Warning Indicators | M1: Risk Owner | N1: Gross Exposure (% TCV) | O1: Gross Exposure (EUR) | P1: Probability Factor | Q1: Expected Monetary Value (EUR) | R1: Mitigation Effectiveness | S1: Residual Exposure (EUR) | T1: Residual Exposure (% TCV) | U1: Quantification Basis | V1: Source Basis
A2: GER-0001 | B2: For a Onshore Wind EPC / Turnkey project in Europe, there is a risk during Feasibility & Concept that ambiguity or conflicting requirements, combined with insufficient planning, may adversely affect project objectives through cost / time consequences. | C2: Contractual | D2: EPC / Turnkey | E2: Onshore Wind | F2: Europe | G2: Feasibility & Concept | H2: Shared | I2: M | J2: Cost / Time | K2: Establish controls for ambiguity or conflicting requirements; assign actions, verify evidence, and review residual exposure at each gate. Tailor the response to Onshore Wind, the Feasibility & Concept gate, local law, interfaces, and the selected delivery model. | L2: Increasing unresolved actions, late milestones, repeated exceptions, or adverse trend associated with insufficient planning. Also monitor phase-gate slippage, unresolved interfaces, supplier status, and regulatory changes in Europe. | M2: Contract Manager | N2: 0.0144 | O2: =N2*'Financial Inputs'!$B$3 -> 1440000 | P2: =IF(I2="L",'Financial Inputs'!$B$4,IF(I2="M",'Financial Inputs'!$B$5,'Financial Inputs'!$B$6)) -> 0.4 | Q2: =O2*P2 -> 576000 | R2: ='Financial Inputs'!$B$7 -> 0.35 | S2: =Q2*(1-R2) -> 374400 | T2: =S2/'Financial Inputs'!$B$3 -> 0.003744 | U2: Parametric screening: exposure % × TCV × probability; residual EMV after mitigation. | V2: Research-informed synthesis: FIDIC risk themes and global construction/energy project literature; not verbatim source text.
A3: GER-0002 | B3: For a Biomass / Waste-to-Energy Installation project in Africa, there is a risk during FEED / Basic Design that ambiguity or conflicting requirements, combined with insufficient planning, may adversely affect project objectives through cost / time consequences. | C3: Contractual | D3: Installation | E3: Biomass / Waste-to-Energy | F3: Africa | G3: FEED / Basic Design | H3: Shared | I3: M | J3: Cost / Time | K3: Establish controls for ambiguity or conflicting requirements; assign actions, verify evidence, and review residual exposure at each gate. Tailor the response to Biomass / Waste-to-Energy, the FEED / Basic Design gate, local law, interfaces, and the selected delivery model. | L3: Increasing unresolved actions, late milestones, repeated exceptions, or adverse trend associated with insufficient planning. Also monitor phase-gate slippage, unresolved interfaces, supplier status, and regulatory changes in Africa. | M3: Contract Manager | N3: 0.0162 | O3: =N3*'Financial Inputs'!$B$3 -> 1620000 | P3: =IF(I3="L",'Financial Inputs'!$B$4,IF(I3="M",'Financial Inputs'!$B$5,'Financial Inputs'!$B$6)) -> 0.4 | Q3: =O3*P3 -> 648000 | R3: ='Financial Inputs'!$B$7 -> 0.35 | S3: =Q3*(1-R3) -> 421200 | T3: =S3/'Financial Inputs'!$B$3 -> 0.004212 | U3: Parametric screening: exposure % × TCV × probability; residual EMV after mitigation. | V3: Research-informed synthesis: FIDIC risk themes and global construction/energy project literature; not verbatim source text.
A4: GER-0003 | B4: For a Oil & Gas Upstream Operations & Maintenance project in East Asia, there is a risk during Detailed Engineering that ambiguity or conflicting requirements, combined with insufficient planning, may adversely affect project objectives through cost / time consequences. | C4: Contractual | D4: Operations & Maintenance | E4: Oil & Gas Upstream | F4: East Asia | G4: Detailed Engineering | H4: Shared | I4: M | J4: Cost / Time | K4: Establish controls for ambiguity or conflicting requirements; assign actions, verify evidence, and review residual exposure at each gate. Tailor the response to Oil & Gas Upstream, the Detailed Engineering gate, local law, interfaces, and the selected delivery model. | L4: Increasing unresolved actions, late milestones, repeated exceptions, or adverse trend associated with insufficient planning. Also monitor phase-gate slippage, unresolved interfaces, supplier status, and regulatory changes in East Asia. | M4: Contract Manager | N4: 0.018 | O4: =N4*'Financial Inputs'!$B$3 -> 1800000 | P4: =IF(I4="L",'Financial Inputs'!$B$4,IF(I4="M",'Financial Inputs'!$B$5,'Financial Inputs'!$B$6)) -> 0.4 | Q4: =O4*P4 -> 720000 | R4: ='Financial Inputs'!$B$7 -> 0.35 | S4: =Q4*(1-R4) -> 468000 | T4: =S4/'Financial Inputs'!$B$3 -> 0.00468 | U4: Parametric screening: exposure % × TCV × probability; residual EMV after mitigation. | V4: Research-informed synthesis: FIDIC risk themes and global construction/energy project literature; not verbatim source text.
A5: GER-0004 | B5: For a Offshore Wind Grid Interconnection project in North America, there is a risk during Procurement that ambiguity or conflicting requirements, combined with insufficient planning, may adversely affect project objectives through cost / time consequences. | C5: Contractual | D5: Grid Interconnection | E5: Offshore Wind | F5: North America | G5: Procurement | H5: Shared | I5: M | J5: Cost / Time | K5: Establish controls for ambiguity or conflicting requirements; assign actions, verify evidence, and review residual exposure at each gate. Tailor the response to Offshore Wind, the Procurement gate, local law, interfaces, and the selected delivery model. | L5: Increasing unresolved actions, late milestones, repeated exceptions, or adverse trend associated with insufficient planning. Also monitor phase-gate slippage, unresolved interfaces, supplier status, and regulatory changes in North America. | M5: Contract Manager | N5: 0.0198 | O5: =N5*'Financial Inputs'!$B$3 -> 1980000 | P5: =IF(I5="L",'Financial Inputs'!$B$4,IF(I5="M",'Financial Inputs'!$B$5,'Financial Inputs'!$B$6)) -> 0.4 | Q5: =O5*P5 -> 792000 | R5: ='Financial Inputs'!$B$7 -> 0.35 | S5: =Q5*(1-R5) -> 514800 | T5: =S5/'Financial Inputs'!$B$3 -> 0.005148 | U5: Parametric screening: exposure % × TCV × probability; residual EMV after mitigation. | V5: Research-informed synthesis: FIDIC risk themes and global construction/energy project literature; not verbatim source text.
A6: GER-0005 | B6: For a Green Hydrogen R&D / Technology Development project in Oceania, there is a risk during Manufacturing that ambiguity or conflicting requirements, combined with insufficient planning, may adversely affect project objectives through cost / time consequences. | C6: Contractual | D6: R&D / Technology Development | E6: Green Hydrogen | F6: Oceania | G6: Manufacturing | H6: Shared | I6: M | J6: Cost / Time | K6: Establish controls for ambiguity or conflicting requirements; assign actions, verify evidence, and review residual exposure at each gate. Tailor the response to Green Hydrogen, the Manufacturing gate, local law, interfaces, and the selected delivery model. | L6: Increasing unresolved actions, late milestones, repeated exceptions, or adverse trend associated with insufficient planning. Also monitor phase-gate slippage, unresolved interfaces, supplier status, and regulatory changes in Oceania. | M6: Contract Manager | N6: 0.0216 | O6: =N6*'Financial Inputs'!$B$3 -> 2160000 | P6: =IF(I6="L",'Financial Inputs'!$B$4,IF(I6="M",'Financial Inputs'!$B$5,'Financial Inputs'!$B$6)) -> 0.4 | Q6: =O6*P6 -> 864000 | R6: ='Financial Inputs'!$B$7 -> 0.35 | S6: =Q6*(1-R6) -> 561600 | T6: =S6/'Financial Inputs'!$B$3 -> 0.005616 | U6: Parametric screening: exposure % × TCV × probability; residual EMV after mitigation. | V6: Research-informed synthesis: FIDIC risk themes and global construction/energy project literature; not verbatim source text.
A7: GER-0006 | B7: For a Concentrated Solar Power EPCM project in Middle East, there is a risk during Detailed Engineering that ambiguity or conflicting requirements, combined with incomplete information, may adversely affect project objectives through cost / time consequences. | C7: Contractual | D7: EPCM | E7: Concentrated Solar Power | F7: Middle East | G7: Detailed Engineering | H7: Shared | I7: M | J7: Cost / Time | K7: Establish controls for ambiguity or conflicting requirements; assign actions, verify evidence, and review residual exposure at each gate. Tailor the response to Concentrated Solar Power, the Detailed Engineering gate, local law, interfaces, and the selected delivery model. | L7: Increasing unresolved actions, late milestones, repeated exceptions, or adverse trend associated with incomplete information. Also monitor phase-gate slippage, unresolved interfaces, supplier status, and regulatory changes in Middle East. | M7: Contract Manager | N7: 0.0144 | O7: =N7*'Financial Inputs'!$B$3 -> 1440000 | P7: =IF(I7="L",'Financial Inputs'!$B$4,IF(I7="M",'Financial Inputs'!$B$5,'Financial Inputs'!$B$6)) -> 0.4 | Q7: =O7*P7 -> 576000 | R7: ='Financial Inputs'!$B$7 -> 0.35 | S7: =Q7*(1-R7) -> 374400 | T7: =S7/'Financial Inputs'!$B$3 -> 0.003744 | U7: Parametric screening: exposure % × TCV × probability; residual EMV after mitigation. | V7: Research-informed synthesis: FIDIC risk themes and global construction/energy project literature; not verbatim source text.
A8: GER-0007 | B8: For a Transmission & Substations Commissioning & Start-up project in South Asia, there is a risk during Procurement that ambiguity or conflicting requirements, combined with incomplete information, may adversely affect project objectives through cost / time consequences. | C8: Contractual | D8: Commissioning & Start-up | E8: Transmission & Substations | F8: South Asia | G8: Procurement | H8: Shared | I8: M | J8: Cost / Time | K8: Establish controls for ambiguity or conflicting requirements; assign actions, verify evidence, and review residual exposure at each gate. Tailor the response to Transmission & Substations, the Procurement gate, local law, interfaces, and the selected delivery model. | L8: Increasing unresolved actions, late milestones, repeated exceptions, or adverse trend associated with incomplete information. Also monitor phase-gate slippage, unresolved interfaces, supplier status, and regulatory changes in South Asia. | M8: Contract Manager | N8: 0.0162 | O8: =N8*'Financial Inputs'!$B$3 -> 1620000 | P8: =IF(I8="L",'Financial Inputs'!$B$4,IF(I8="M",'Financial Inputs'!$B$5,'Financial Inputs'!$B$6)) -> 0.4 | Q8: =O8*P8 -> 648000 | R8: ='Financial Inputs'!$B$7 -> 0.35 | S8: =Q8*(1-R8) -> 421200 | T8: =S8/'Financial Inputs'!$B$3 -> 0.004212 | U8: Parametric screening: exposure % × TCV × probability; residual EMV after mitigation. | V8: Research-informed synthesis: FIDIC risk themes and global construction/energy project literature; not verbatim source text.
A9: GER-0008 | B9: For a Carbon Capture, Utilization & Storage Decommissioning project in Southeast Asia, there is a risk during Manufacturing that ambiguity or conflicting requirements, combined with incomplete information, may adversely affect project objectives through cost / time consequences. | C9: Contractual | D9: Decommissioning | E9: Carbon Capture, Utilization & Storage | F9: Southeast Asia | G9: Manufacturing | H9: Shared | I9: M | J9: Cost / Time | K9: Establish controls for ambiguity or conflicting requirements; assign actions, verify evidence, and review residual exposure at each gate. Tailor the response to Carbon Capture, Utilization & Storage, the Manufacturing gate, local law, interfaces, and the selected delivery model. | L9: Increasing unresolved actions, late milestones, repeated exceptions, or adverse trend associated with incomplete information. Also monitor phase-gate slippage, unresolved interfaces, supplier status, and regulatory changes in Southeast Asia. | M9: Contract Manager | N9: 0.018 | O9: =N9*'Financial Inputs'!$B$3 -> 1800000 | P9: =IF(I9="L",'Financial Inputs'!$B$4,IF(I9="M",'Financial Inputs'!$B$5,'Financial Inputs'!$B$6)) -> 0.4 | Q9: =O9*P9 -> 720000 | R9: ='Financial Inputs'!$B$7 -> 0.35 | S9: =Q9*(1-R9) -> 468000 | T9: =S9/'Financial Inputs'!$B$3 -> 0.00468 | U9: Parametric screening: exposure % × TCV × probability; residual EMV after mitigation. | V9: Research-informed synthesis: FIDIC risk themes and global construction/energy project literature; not verbatim source text.
A10: GER-0009 | B10: For a Hydropower EPC / Turnkey project in Latin America, there is a risk during Construction that ambiguity or conflicting requirements, combined with incomplete information, may adversely affect project objectives through cost / time consequences. | C10: Contractual | D10: EPC / Turnkey | E10: Hydropower | F10: Latin America | G10: Construction | H10: Shared | I10: M | J10: Cost / Time | K10: Establish controls for ambiguity or conflicting requirements; assign actions, verify evidence, and review residual exposure at each gate. Tailor the response to Hydropower, the Construction gate, local law, interfaces, and the selected delivery model. | L10: Increasing unresolved actions, late milestones, repeated exceptions, or adverse trend associated with incomplete information. Also monitor phase-gate slippage, unresolved interfaces, supplier status, and regulatory changes in Latin America. | M10: Contract Manager | N10: 0.0198 | O10: =N10*'Financial Inputs'!$B$3 -> 1980000 | P10: =IF(I10="L",'Financial Inputs'!$B$4,IF(I10="M",'Financial Inputs'!$B$5,'Financial Inputs'!$B$6)) -> 0.4 | Q10: =O10*P10 -> 792000 | R10: ='Financial Inputs'!$B$7 -> 0.35 | S10: =Q10*(1-R10) -> 514800 | T10: =S10/'Financial Inputs'!$B$3 -> 0.005148 | U10: Parametric screening: exposure % × TCV × probability; residual EMV after mitigation. | V10: Research-informed synthesis: FIDIC risk themes and global construction/energy project literature; not verbatim source text.
A11: GER-0010 | B11: For a Nuclear Power Installation project in Global / Multi-country, there is a risk during Installation that ambiguity or conflicting requirements, combined with incomplete information, may adversely affect project objectives through cost / time consequences. | C11: Contractual | D11: Installation | E11: Nuclear Power | F11: Global / Multi-country | G11: Installation | H11: Shared | I11: M | J11: Cost / Time | K11: Establish controls for ambiguity or conflicting requirements; assign actions, verify evidence, and review residual exposure at each gate. Tailor the response to Nuclear Power, the Installation gate, local law, interfaces, and the selected delivery model. | L11: Increasing unresolved actions, late milestones, repeated exceptions, or adverse trend associated with incomplete information. Also monitor phase-gate slippage, unresolved interfaces, supplier status, and regulatory changes in Global / Multi-country. | M11: Contract Manager | N11: 0.0216 | O11: =N11*'Financial Inputs'!$B$3 -> 2160000 | P11: =IF(I11="L",'Financial Inputs'!$B$4,IF(I11="M",'Financial Inputs'!$B$5,'Financial Inputs'!$B$6)) -> 0.4 | Q11: =O11*P11 -> 864000 | R11: ='Financial Inputs'!$B$7 -> 0.35 | S11: =Q11*(1-R11) -> 561600 | T11: =S11/'Financial Inputs'!$B$3 -> 0.005616 | U11: Parametric screening: exposure % × TCV × probability; residual EMV after mitigation. | V11: Research-informed synthesis: FIDIC risk themes and global construction/energy project literature; not verbatim source text.
A12: GER-0011 | B12: For a Geothermal R&D / Technology Development project in Africa, there is a risk during Manufacturing that ambiguity or conflicting requirements, combined with late decision-making, may adversely affect project objectives through cost / time consequences. | C12: Contractual | D12: R&D / Technology Development | E12: Geothermal | F12: Africa | G12: Manufacturing | H12: Shared | I12: M | J12: Cost / Time | K12: Establish controls for ambiguity or conflicting requirements; assign actions, verify evidence, and review residual exposure at each gate. Tailor the response to Geothermal, the Manufacturing gate, local law, interfaces, and the selected delivery model. | L12: Increasing unresolved actions, late milestones, repeated exceptions, or adverse trend associated with late decision-making. Also monitor phase-gate slippage, unresolved interfaces, supplier status, and regulatory changes in Africa. | M12: Contract Manager | N12: 0.0144 | O12: =N12*'Financial Inputs'!$B$3 -> 1440000 | P12: =IF(I12="L",'Financial Inputs'!$B$4,IF(I12="M",'Financial Inputs'!$B$5,'Financial Inputs'!$B$6)) -> 0.4 | Q12: =O12*P12 -> 576000 | R12: ='Financial Inputs'!$B$7 -> 0.35 | S12: =Q12*(1-R12) -> 374400 | T12: =S12/'Financial Inputs'!$B$3 -> 0.003744 | U12: Parametric screening: exposure % × TCV × probability; residual EMV after mitigation. | V12: Research-informed synthesis: FIDIC risk themes and global construction/energy project literature; not verbatim source text.
A13: GER-0012 | B13: For a LNG Brownfield Modification project in East Asia, there is a risk during Construction that ambiguity or conflicting requirements, combined with late decision-making, may adversely affect project objectives through cost / time consequences. | C13: Contractual | D13: Brownfield Modification | E13: LNG | F13: East Asia | G13: Construction | H13: Shared | I13: M | J13: Cost / Time | K13: Establish controls for ambiguity or conflicting requirements; assign actions, verify evidence, and review residual exposure at each gate. Tailor the response to LNG, the Construction gate, local law, interfaces, and the selected delivery model. | L13: Increasing unresolved actions, late milestones, repeated exceptions, or adverse trend associated with late decision-making. Also monitor phase-gate slippage, unresolved interfaces, supplier status, and regulatory changes in East Asia. | M13: Contract Manager | N13: 0.0162 | O13: =N13*'Financial Inputs'!$B$3 -> 1620000 | P13: =IF(I13="L",'Financial Inputs'!$B$4,IF(I13="M",'Financial Inputs'!$B$5,'Financial Inputs'!$B$6)) -> 0.4 | Q13: =O13*P13 -> 648000 | R13: ='Financial Inputs'!$B$7 -> 0.35 | S13: =Q13*(1-R13) -> 421200 | T13: =S13/'Financial Inputs'!$B$3 -> 0.004212 | U13: Parametric screening: exposure % × TCV × probability; residual EMV after mitigation. | V13: Research-informed synthesis: FIDIC risk themes and global construction/energy project literature; not verbatim source text.
... A3001: GER-3000 | B3001: For a Pumped Storage EPCM project in Latin America, there is a risk during Detailed Engineering that coverage gap, theft, vandalism or security incident, combined with performance variability, may adversely affect project objectives through cost / time consequences. | C3001: Insurance & Security | D3001: EPCM | E3001: Pumped Storage | F3001: Latin America | G3001: Detailed Engineering | H3001: Shared | I3001: L | J3001: Cost / Time | K3001: Establish controls for coverage gap, theft, vandalism or security incident; assign actions, verify evidence, and review residual exposure at each gate. Tailor the response to Pumped Storage, the Detailed Engineering gate, local law, interfaces, and the selected delivery model. | L3001: Increasing unresolved actions, late milestones, repeated exceptions, or adverse trend associated with performance variability. Also monitor phase-gate slippage, unresolved interfaces, supplier status, and regulatory changes in Latin America. | M3001: Risk & Insurance Manager | N3001: 0.012 | O3001: =N3001*'Financial Inputs'!$B$3 -> 1200000 | P3001: =IF(I3001="L",'Financial Inputs'!$B$4,IF(I3001="M",'Financial Inputs'!$B$5,'Financial Inputs'!$B$6)) -> 0.15 | Q3001: =O3001*P3001 -> 180000 | R3001: ='Financial Inputs'!$B$7 -> 0.35 | S3001: =Q3001*(1-R3001) -> 117000 | T3001: =S3001/'Financial Inputs'!$B$3 -> 0.00117 | U3001: Parametric screening: exposure % × TCV × probability; residual EMV after mitigation. | V3001: Research-informed synthesis: FIDIC risk themes and global construction/energy project literature; not verbatim source text.

Sheet Category Summary
A1: Global Energy Project Risk Library: 3,000-Risk Summary
A3: Risk Category | B3: Risk Count | C3: Share of Library | D3: High Probability | E3: Contractor Allocated | F3: Employer Allocated | G3: Shared Allocation
A4: Contractual | B4: =COUNTIF('Risk Library'!$C$2:$C$3001,A4) -> 100 | C4: =B4/$B$34 -> 0.033333333 | D4: =COUNTIFS('Risk Library'!$C$2:$C$3001,A4,'Risk Library'!$I$2:$I$3001,"H") -> 0 | E4: =COUNTIFS('Risk Library'!$C$2:$C$3001,A4,'Risk Library'!$H$2:$H$3001,"Contractor") -> 0 | F4: =COUNTIFS('Risk Library'!$C$2:$C$3001,A4,'Risk Library'!$H$2:$H$3001,"Employer") -> 0 | G4: =COUNTIFS('Risk Library'!$C$2:$C$3001,A4,'Risk Library'!$H$2:$H$3001,"Shared") -> 100
A5: Schedule | B5: =COUNTIF('Risk Library'!$C$2:$C$3001,A5) -> 100 | C5: =B5/$B$34 -> 0.033333333 | D5: =COUNTIFS('Risk Library'!$C$2:$C$3001,A5,'Risk Library'!$I$2:$I$3001,"H") -> 100 | E5: =COUNTIFS('Risk Library'!$C$2:$C$3001,A5,'Risk Library'!$H$2:$H$3001,"Contractor") -> 100 | F5: =COUNTIFS('Risk Library'!$C$2:$C$3001,A5,'Risk Library'!$H$2:$H$3001,"Employer") -> 0 | G5: =COUNTIFS('Risk Library'!$C$2:$C$3001,A5,'Risk Library'!$H$2:$H$3001,"Shared") -> 0
A6: Cost & Estimating | B6: =COUNTIF('Risk Library'!$C$2:$C$3001,A6) -> 100 | C6: =B6/$B$34 -> 0.033333333 | D6: =COUNTIFS('Risk Library'!$C$2:$C$3001,A6,'Risk Library'!$I$2:$I$3001,"H") -> 100 | E6: =COUNTIFS('Risk Library'!$C$2:$C$3001,A6,'Risk Library'!$H$2:$H$3001,"Contractor") -> 100 | F6: =COUNTIFS('Risk Library'!$C$2:$C$3001,A6,'Risk Library'!$H$2:$H$3001,"Employer") -> 0 | G6: =COUNTIFS('Risk Library'!$C$2:$C$3001,A6,'Risk Library'!$H$2:$H$3001,"Shared") -> 0
A7: Design & Engineering | B7: =COUNTIF('Risk Library'!$C$2:$C$3001,A7) -> 100 | C7: =B7/$B$34 -> 0.033333333 | D7: =COUNTIFS('Risk Library'!$C$2:$C$3001,A7,'Risk Library'!$I$2:$I$3001,"H") -> 100 | E7: =COUNTIFS('Risk Library'!$C$2:$C$3001,A7,'Risk Library'!$H$2:$H$3001,"Contractor") -> 100 | F7: =COUNTIFS('Risk Library'!$C$2:$C$3001,A7,'Risk Library'!$H$2:$H$3001,"Employer") -> 0 | G7: =COUNTIFS('Risk Library'!$C$2:$C$3001,A7,'Risk Library'!$H$2:$H$3001,"Shared") -> 0
A8: Quality & Defects | B8: =COUNTIF('Risk Library'!$C$2:$C$3001,A8) -> 100 | C8: =B8/$B$34 -> 0.033333333 | D8: =COUNTIFS('Risk Library'!$C$2:$C$3001,A8,'Risk Library'!$I$2:$I$3001,"H") -> 0 | E8: =COUNTIFS('Risk Library'!$C$2:$C$3001,A8,'Risk Library'!$H$2:$H$3001,"Contractor") -> 100 | F8: =COUNTIFS('Risk Library'!$C$2:$C$3001,A8,'Risk Library'!$H$2:$H$3001,"Employer") -> 0 | G8: =COUNTIFS('Risk Library'!$C$2:$C$3001,A8,'Risk Library'!$H$2:$H$3001,"Shared") -> 0
A9: HSE | B9: =COUNTIF('Risk Library'!$C$2:$C$3001,A9) -> 100 | C9: =B9/$B$34 -> 0.033333333 | D9: =COUNTIFS('Risk Library'!$C$2:$C$3001,A9,'Risk Library'!$I$2:$I$3001,"H") -> 0 | E9: =COUNTIFS('Risk Library'!$C$2:$C$3001,A9,'Risk Library'!$H$2:$H$3001,"Contractor") -> 100 | F9: =COUNTIFS('Risk Library'!$C$2:$C$3001,A9,'Risk Library'!$H$2:$H$3001,"Employer") -> 0 | G9: =COUNTIFS('Risk Library'!$C$2:$C$3001,A9,'Risk Library'!$H$2:$H$3001,"Shared") -> 0
A10: Environmental | B10: =COUNTIF('Risk Library'!$C$2:$C$3001,A10) -> 100 | C10: =B10/$B$34 -> 0.033333333 | D10: =COUNTIFS('Risk Library'!$C$2:$C$3001,A10,'Risk Library'!$I$2:$I$3001,"H") -> 0 | E10: =COUNTIFS('Risk Library'!$C$2:$C$3001,A10,'Risk Library'!$H$2:$H$3001,"Contractor") -> 0 | F10: =COUNTIFS('Risk Library'!$C$2:$C$3001,A10,'Risk Library'!$H$2:$H$3001,"Employer") -> 0 | G10: =COUNTIFS('Risk Library'!$C$2:$C$3001,A10,'Risk Library'!$H$2:$H$3001,"Shared") -> 100
A11: Political & Country | B11: =COUNTIF('Risk Library'!$C$2:$C$3001,A11) -> 100 | C11: =B11/$B$34 -> 0.033333333 | D11: =COUNTIFS('Risk Library'!$C$2:$C$3001,A11,'Risk Library'!$I$2:$I$3001,"H") -> 0 | E11: =COUNTIFS('Risk Library'!$C$2:$C$3001,A11,'Risk Library'!$H$2:$H$3001,"Contractor") -> 0 | F11: =COUNTIFS('Risk Library'!$C$2:$C$3001,A11,'Risk Library'!$H$2:$H$3001,"Employer") -> 100 | G11: =COUNTIFS('Risk Library'!$C$2:$C$3001,A11,'Risk Library'!$H$2:$H$3001,"Shared") -> 0
A12: Regulatory & Change in Law | B12: =COUNTIF('Risk Library'!$C$2:$C$3001,A12) -> 100 | C12: =B12/$B$34 -> 0.033333333 | D12: =COUNTIFS('Risk Library'!$C$2:$C$3001,A12,'Risk Library'!$I$2:$I$3001,"H") -> 0 | E12: =COUNTIFS('Risk Library'!$C$2:$C$3001,A12,'Risk Library'!$H$2:$H$3001,"Contractor") -> 0 | F12: =COUNTIFS('Risk Library'!$C$2:$C$3001,A12,'Risk Library'!$H$2:$H$3001,"Employer") -> 0 | G12: =COUNTIFS('Risk Library'!$C$2:$C$3001,A12,'Risk Library'!$H$2:$H$3001,"Shared") -> 100
A13: Permits & Approvals | B13: =COUNTIF('Risk Library'!$C$2:$C$3001,A13) -> 100 | C13: =B13/$B$34 -> 0.033333333 | D13: =COUNTIFS('Risk Library'!$C$2:$C$3001,A13,'Risk Library'!$I$2:$I$3001,"H") -> 100 | E13: =COUNTIFS('Risk Library'!$C$2:$C$3001,A13,'Risk Library'!$H$2:$H$3001,"Contractor") -> 0 | F13: =COUNTIFS('Risk Library'!$C$2:$C$3001,A13,'Risk Library'!$H$2:$H$3001,"Employer") -> 100 | G13: =COUNTIFS('Risk Library'!$C$2:$C$3001,A13,'Risk Library'!$H$2:$H$3001,"Shared") -> 0
A14: Site & Ground Conditions | B14: =COUNTIF('Risk Library'!$C$2:$C$3001,A14) -> 100 | C14: =B14/$B$34 -> 0.033333333 | D14: =COUNTIFS('Risk Library'!$C$2:$C$3001,A14,'Risk Library'!$I$2:$I$3001,"H") -> 0 | E14: =COUNTIFS('Risk Library'!$C$2:$C$3001,A14,'Risk Library'!$H$2:$H$3001,"Contractor") -> 0 | F14: =COUNTIFS('Risk Library'!$C$2:$C$3001,A14,'Risk Library'!$H$2:$H$3001,"Employer") -> 0 | G14: =COUNTIFS('Risk Library'!$C$2:$C$3001,A14,'Risk Library'!$H$2:$H$3001,"Shared") -> 100
A15: Weather & Natural Hazards | B15: =COUNTIF('Risk Library'!$C$2:$C$3001,A15) -> 100 | C15: =B15/$B$34 -> 0.033333333 | D15: =COUNTIFS('Risk Library'!$C$2:$C$3001,A15,'Risk Library'!$I$2:$I$3001,"H") -> 0 | E15: =COUNTIFS('Risk Library'!$C$2:$C$3001,A15,'Risk Library'!$H$2:$H$3001,"Contractor") -> 0 | F15: =COUNTIFS('Risk Library'!$C$2:$C$3001,A15,'Risk Library'!$H$2:$H$3001,"Employer") -> 0 | G15: =COUNTIFS('Risk Library'!$C$2:$C$3001,A15,'Risk Library'!$H$2:$H$3001,"Shared") -> 100
... A33: Insurance & Security | B33: =COUNTIF('Risk Library'!$C$2:$C$3001,A33) -> 100 | C33: =B33/$B$34 -> 0.033333333 | D33: =COUNTIFS('Risk Library'!$C$2:$C$3001,A33,'Risk Library'!$I$2:$I$3001,"H") -> 0 | E33: =COUNTIFS('Risk Library'!$C$2:$C$3001,A33,'Risk Library'!$H$2:$H$3001,"Contractor") -> 0 | F33: =COUNTIFS('Risk Library'!$C$2:$C$3001,A33,'Risk Library'!$H$2:$H$3001,"Employer") -> 0 | G33: =COUNTIFS('Risk Library'!$C$2:$C$3001,A33,'Risk Library'!$H$2:$H$3001,"Shared") -> 100
A34: Total | B34: =SUM(B4:B33) -> 3000 | C34: =SUM(C4:C33) -> 1

Sheet Coverage Matrix
A1: Coverage Dimensions
A3: Dimension | B3: Included Values | C3: Number of Values | D3: Application Note
A4: Project types | B4: EPC / Turnkey, EPCM, R&D / Technology Development, Installation, Commissioning & Start-up, Brownfield Modification, Operations & Maintenance, Decommissioning, Owner’s Engineering, Grid Interconnection | C4: 10 | D4: Use filters to isolate the relevant delivery model.
A5: Energy segments | B5: Onshore Wind, Offshore Wind, Solar PV, Concentrated Solar Power, Hydropower, Pumped Storage, Geothermal, Biomass / Waste-to-Energy, Green Hydrogen, Battery Energy Storage, Transmission & Substations, Nuclear Power, Natural Gas / CCGT, LNG, Oil & Gas Upstream, Refining & Petrochemicals, Coal / Thermal Power, Carbon Capture, Utilization & Storage, District Energy, Marine Energy | C5: 20 | D5: Covers renewable, low-carbon and conventional energy.
A6: Geographic contexts | B6: Europe, Middle East, Africa, South Asia, East Asia, Southeast Asia, North America, Latin America, Oceania, Global / Multi-country | C6: 10 | D6: Regional labels are screening contexts, not country-specific legal conclusions.
A7: Lifecycle phases | B7: Feasibility & Concept, FEED / Basic Design, Detailed Engineering, Procurement, Manufacturing, Construction, Installation, Pre-commissioning, Commissioning, Operations / Handover | C7: 10 | D7: Risks are contextualized from concept through handover and operations.
A8: Risk categories | B8: Contractual, Schedule, Cost & Estimating, Design & Engineering, Quality & Defects, HSE, Environmental, Political & Country, Regulatory & Change in Law, Permits & Approvals, Site & Ground Conditions, Weather & Natural Hazards, Force Majeure / Exceptional Events, Procurement & Supply Chain, Logistics & Customs, Labour & Skills, Plant & Equipment, Interfaces, Stakeholder & Community, Land & Right of Way, Payment & Cash Flow, Claims & Disputes, Change & Scope, Technology & Maturity, Digital, Data & Cybersecurity, Commissioning & Start-up, Operations & Maintainability, Governance & Decision Making, Fraud, Ethics & Compliance, Insurance & Security | C8: 30 | D8: Categories synthesize contractual and research-based risk themes.

Sheet Method & Sources
A1: Method, Limitations and Research Basis
A3: Deliverable | B3: 3,000 distinct contextualized risk statements created by extending 600 seed risks across project type, energy technology, geography and lifecycle dimensions.
A4: Important limitation | B4: This is a research-informed synthesis, not a claim to contain every risk from every publication worldwide. It does not reproduce copyrighted FIDIC clauses or journal text verbatim.
A5: Use of probability | B5: L/M/H values are initial screening defaults inherited from the category-level seed library. Reassess them using project evidence and an approved scoring matrix.
A6: Use of allocation | B6: Employer, Contractor and Shared allocations are screening assumptions. The signed contract, Particular Conditions, governing law and project facts control actual allocation.
A7: Attached research article | B7: Dikmen, Eken, Erol and Birgonul (2025), Computers in Industry 166, 104251. https://doi.org/10.1016/j.compind.2025.104251
A8: Systematic review | B8: Su and Khallaf (2022), Sustainability 14, 6412. https://doi.org/10.3390/su14116412
A9: Taxonomic review | B9: Sarvari (2026), Eng 7, 380. https://doi.org/10.3390/eng7080380
A10: Energy investment context | B10: International Energy Agency, World Energy Investment 2025. https://www.iea.org/reports/world-energy-investment-2025
A11: EPC text-mining study | B11: Choi et al. (2021), Energies 14, 4632. https://doi.org/10.3390/en14154632
A12: Recommended workflow | B12: Filter by energy segment, project type and lifecycle phase; workshop probability and impact; assign a named accountable owner; link each selected risk to project evidence and controls.
A14: Monetary quantification | B14: Gross exposure equals a category-based percentage of editable Total Contract Value. EMV equals gross exposure multiplied by the L/M/H probability factor. Residual exposure equals EMV multiplied by one minus mitigation effectiveness. These are parametric screening assumptions, not article-derived monetary estimates.
